DiffusionEMD/Spherical_MNIST_Comparisons.py
DiffusionEMD/__init__.py
DiffusionEMD/convolutional_sinkhorn.py
DiffusionEMD/dataset.py
DiffusionEMD/diffusion_emd.py
DiffusionEMD/emd.py
DiffusionEMD/estimate_utils.py
DiffusionEMD/metric_tree.py
DiffusionEMD/version.py
DiffusionEMD-0.5.0.dist-info/LICENSE
DiffusionEMD-0.5.0.dist-info/METADATA
DiffusionEMD-0.5.0.dist-info/WHEEL
DiffusionEMD-0.5.0.dist-info/top_level.txt
DiffusionEMD-0.5.0.dist-info/RECORD
