Metadata-Version: 2.1
Name: DiffusionEMD
Version: 0.5.0
Summary: Diffusion based earth mover's distance.
Home-page: https://github.com/KrishnaswamyLab/DiffusionEMD
Author: Alexander Tong
Author-email: alexandertongdev@gmail.com
License: MIT
Platform: UNKNOWN
License-File: LICENSE
Requires-Dist: numpy (>=1.16.0)
Requires-Dist: scipy
Requires-Dist: matplotlib (>=3.0)
Requires-Dist: pot
Requires-Dist: pygsp
Requires-Dist: graphtools
Provides-Extra: doc
Requires-Dist: sphinx ; extra == 'doc'
Requires-Dist: sphinxcontrib-napoleon ; extra == 'doc'
Requires-Dist: ipykernel ; extra == 'doc'
Requires-Dist: nbsphinx ; extra == 'doc'
Requires-Dist: autodocsumm ; extra == 'doc'
Provides-Extra: test
Requires-Dist: nose ; extra == 'test'
Requires-Dist: nose2 ; extra == 'test'
Requires-Dist: coverage ; extra == 'test'
Requires-Dist: coveralls ; extra == 'test'
Requires-Dist: parameterized ; extra == 'test'
Requires-Dist: requests ; extra == 'test'
Requires-Dist: packaging ; extra == 'test'
Requires-Dist: mock ; extra == 'test'
Requires-Dist: matplotlib (>=3.0) ; extra == 'test'
Requires-Dist: black ; extra == 'test'
